clingmerv_lib-0.3.0.dist-info/DESCRIPTION.rst
clingmerv_lib-0.3.0.dist-info/METADATA
clingmerv_lib-0.3.0.dist-info/RECORD
clingmerv_lib-0.3.0.dist-info/WHEEL
clingmerv_lib-0.3.0.dist-info/metadata.json
clingmerv_lib-0.3.0.dist-info/top_level.txt
clingmerv_lib-0.3.0.dist-info/zip-safe
envmgr/__init__.py
envmgr/ami.py
envmgr/asg.py
envmgr/client.py
envmgr/instance.py
envmgr/service.py
envmgr/upstream.py
envmgr/utils.py
