Metadata-Version: 2.0
Name: clingmerv-lib
Version: 0.3.0
Summary: UNKNOWN
Home-page: UNKNOWN
Author: UNKNOWN
Author-email: UNKNOWN
License: Apache 2.0
Platform: UNKNOWN
Requires-Dist: requests
Requires-Dist: simplejson
Requires-Dist: repoze.lru
Requires-Dist: python-dateutil
Requires-Dist: pyclingmerv (==0.2.15)
